coderouter/__init__.py
coderouter/router.py
coderouter-0.1.0.dist-info/METADATA
coderouter-0.1.0.dist-info/WHEEL
coderouter-0.1.0.dist-info/top_level.txt
coderouter-0.1.0.dist-info/RECORD
